unitrevpy/__init__.py
unitrevpy/__version__.py
unitrevpy/convert.py
unitrevpy/units/__init__.py
unitrevpy/units/area.py
unitrevpy/units/length.py
unitrevpy/units/temperature.py
unitrevpy/units/time.py
unitrevpy/units/unit.py
unitrevpy/units/volume.py
unitrevpy/units/weight.py
unitrevpy-0.0.4.dist-info/LICENSE
unitrevpy-0.0.4.dist-info/METADATA
unitrevpy-0.0.4.dist-info/WHEEL
unitrevpy-0.0.4.dist-info/top_level.txt
unitrevpy-0.0.4.dist-info/RECORD
