Metadata-Version: 2.1
Name: unitrevpy
Version: 0.0.4
Summary: This contains common unit conversions
Home-page: https://github.com/addleonel/unitrevpy
Author: A. D. Leonel
Author-email: adleonel@gmail.com
License: MIT
Keywords: unit,convert,conversion
Platform: UNKNOWN
Classifier: Programming Language :: Python :: 3
Classifier: License :: OSI Approved :: MIT License
Classifier: Operating System :: OS Independent
Requires-Python: >=3.6
Requires-Dist: numpy
